setup.py
bin/bquick
bquick/__init__.py
bquick/command_parser.py
bquick/config_parser.py
bquick/test_command_parser.py
bquick/test_config_parser.py
bquick.egg-info/PKG-INFO
bquick.egg-info/SOURCES.txt
bquick.egg-info/dependency_links.txt
bquick.egg-info/not-zip-safe
bquick.egg-info/requires.txt
bquick.egg-info/top_level.txt
bquick/bigquery/__init__.py
bquick/bigquery/data_delete_handler.py
bquick/bigquery/table_copy_handler.py
bquick/bigquery/table_delete_handler.py
bquick/bigquery/table_list_handler.py
bquick/bigquery/utils.py