Metadata-Version: 1.0
Name: bquick
Version: 0.1.9
Summary: The command line tool for BigQuery management.
Home-page: http://github.com/visualskyrim/bquick
Author: visualskyrim
Author-email: visual.skyrim@gmail.com
License: MIT
Platform: UNKNOWN
